tailscale_lambda_proxy/__init__.py
tailscale_lambda_proxy/py.typed
tailscale_lambda_proxy/_jsii/__init__.py
tailscale_lambda_proxy/_jsii/tailscale-lambda-proxy@0.0.12.jsii.tgz
tailscale_lambda_proxy-0.0.12.dist-info/LICENSE
tailscale_lambda_proxy-0.0.12.dist-info/METADATA
tailscale_lambda_proxy-0.0.12.dist-info/WHEEL
tailscale_lambda_proxy-0.0.12.dist-info/top_level.txt
tailscale_lambda_proxy-0.0.12.dist-info/RECORD
